gmail_imap_mcp/__init__.py
gmail_imap_mcp/auth.py
gmail_imap_mcp/imap_client.py
gmail_imap_mcp/server.py
iflow_mcp_tonykipkemboi_gmail_imap_mcp-0.1.0.dist-info/METADATA
iflow_mcp_tonykipkemboi_gmail_imap_mcp-0.1.0.dist-info/WHEEL
iflow_mcp_tonykipkemboi_gmail_imap_mcp-0.1.0.dist-info/entry_points.txt
iflow_mcp_tonykipkemboi_gmail_imap_mcp-0.1.0.dist-info/RECORD
