Metadata-Version: 2.4
Name: iflow-mcp_tonykipkemboi_gmail-imap-mcp
Version: 0.1.0
Summary: A Gmail MCP server using IMAP
Author-email: Tony Kipkemboi <iamtonykipkemboi@gmail.com>
Requires-Python: >=3.11
Requires-Dist: google-api-python-client>=2.120.0
Requires-Dist: google-auth-oauthlib>=1.2.0
Requires-Dist: google-auth>=2.28.0
Requires-Dist: imaplib2>=3.6
Requires-Dist: mcp>=1.3.0
Requires-Dist: pydantic>=2.6.0
